MANIFEST.in
README.md
setup.py
activation/__init__.py
activation/activate.so
activation_hard.egg-info/PKG-INFO
activation_hard.egg-info/SOURCES.txt
activation_hard.egg-info/dependency_links.txt
activation_hard.egg-info/requires.txt
activation_hard.egg-info/top_level.txt